odoo/addons/web_m2x_options/README.rst
odoo/addons/web_m2x_options/__init__.py
odoo/addons/web_m2x_options/__manifest__.py
odoo/addons/web_m2x_options/i18n/ar.po
odoo/addons/web_m2x_options/i18n/de.po
odoo/addons/web_m2x_options/i18n/es.po
odoo/addons/web_m2x_options/i18n/fi.po
odoo/addons/web_m2x_options/i18n/fr.po
odoo/addons/web_m2x_options/i18n/hr.po
odoo/addons/web_m2x_options/i18n/it.po
odoo/addons/web_m2x_options/i18n/nl_NL.po
odoo/addons/web_m2x_options/i18n/pt_BR.po
odoo/addons/web_m2x_options/i18n/sl.po
odoo/addons/web_m2x_options/i18n/tr.po
odoo/addons/web_m2x_options/i18n/web_m2x_options.pot
odoo/addons/web_m2x_options/models/__init__.py
odoo/addons/web_m2x_options/models/ir_config_parameter.py
odoo/addons/web_m2x_options/readme/CONTRIBUTORS.rst
odoo/addons/web_m2x_options/readme/DESCRIPTION.rst
odoo/addons/web_m2x_options/readme/ROADMAP.rst
odoo/addons/web_m2x_options/readme/USAGE.rst
odoo/addons/web_m2x_options/static/description/icon.png
odoo/addons/web_m2x_options/static/description/index.html
odoo/addons/web_m2x_options/static/src/js/form.js
odoo/addons/web_m2x_options/static/src/xml/base.xml
odoo/addons/web_m2x_options/views/view.xml
odoo11_addon_web_m2x_options-11.0.1.0.0.99.dev11.dist-info/METADATA
odoo11_addon_web_m2x_options-11.0.1.0.0.99.dev11.dist-info/WHEEL
odoo11_addon_web_m2x_options-11.0.1.0.0.99.dev11.dist-info/top_level.txt
odoo11_addon_web_m2x_options-11.0.1.0.0.99.dev11.dist-info/RECORD
